<?xml version="1.0"?>
<!DOCTYPE hibernate-mapping PUBLIC "-//Hibernate/Hibernate Mapping DTD 3.0//EN"
"http://hibernate.sourceforge.net/hibernate-mapping-3.0.dtd">
<!-- Generated 30-nov-2007 8:26:55 by Hibernate Tools 3.2.0.CR1 -->
<hibernate-mapping>
    <class name="com.kirolak.Match" table="matches" >
        <id name="id" type="int" unsaved-value="-1">
            <column name="id" />
			<generator class="native" />
        </id>      
        <many-to-one name="round" class="com.kirolak.Round">
        	<column name="round_id" />
        	<column name="group_id" />
        </many-to-one>
        <many-to-one name="homeTeam" class="com.kirolak.Team" lazy="false">
            <column name="home_team_id" />
        </many-to-one>
        <many-to-one name="visitingTeam" class="com.kirolak.Team" lazy="false">
            <column name="visiting_team_id" />
        </many-to-one>
        <property name="homeTeamScore" type="java.lang.Short">
            <column name="home_team_score" />
        </property>
        <property name="visitingTeamScore" type="java.lang.Short">
            <column name="visiting_team_score" />
        </property>
        <property name="matchStatus" type="java.lang.Byte">
            <column name="match_status">
                <comment>playing, finished, cancelled...</comment>
            </column>
        </property>
        <property name="dayTime" type="timestamp">
            <column name="day_time" length="0" />
        </property>
        <property name="updated" type="timestamp">
            <column name="updated" length="0" />
        </property>
    </class>
</hibernate-mapping>
